LICENSE
MANIFEST.in
README.md
pyproject.toml
setup.cfg
setup.py
lain.egg-info/PKG-INFO
lain.egg-info/SOURCES.txt
lain.egg-info/dependency_links.txt
lain.egg-info/entry_points.txt
lain.egg-info/not-zip-safe
lain.egg-info/requires.txt
lain.egg-info/top_level.txt
lain_cli/__init__.py
lain_cli/aliyun.py
lain_cli/harbor.py
lain_cli/kibana.py
lain_cli/lain.py
lain_cli/lint.py
lain_cli/prometheus.py
lain_cli/prompt.py
lain_cli/registry.py
lain_cli/scm.py
lain_cli/tencent.py
lain_cli/utils.py
lain_cli/webhook.py
lain_cli/chart_template/Chart.yaml.j2
lain_cli/chart_template/index.yaml
lain_cli/chart_template/values.yaml.j2
lain_cli/chart_template/templates/_helpers.tpl
lain_cli/chart_template/templates/cronjob.yaml
lain_cli/chart_template/templates/deployment.yaml
lain_cli/chart_template/templates/externalIngress.yaml
lain_cli/chart_template/templates/ingress.yaml
lain_cli/chart_template/templates/job.yaml
lain_cli/chart_template/templates/networkPolicy.yaml
lain_cli/chart_template/templates/pvc.yaml
lain_cli/chart_template/templates/service.yaml
lain_cli/chart_template/templates/statefulSet.yaml
lain_cli/chart_template/templates/test.yaml
lain_cli/cluster_values/values-test.yaml
lain_cli/templates/.dockerignore.j2
lain_cli/templates/Dockerfile.j2
lain_cli/templates/canary-toast.txt.j2
lain_cli/templates/deploy-toast.txt.j2
lain_cli/templates/deploy-webhook-message.txt.j2
lain_cli/templates/docker-compose.yaml.j2
lain_cli/templates/job.yaml.j2
lain_cli/templates/k8s-secret-diff.txt.j2
lain_cli/templates/values-canary.yaml.j2
tests/__init__.py
tests/conftest.py
tests/editor.py
tests/test_commands.py
tests/test_utils.py
tests/test_values.py
tests/test_workflow.py