Metadata-Version: 2.1
Name: lain
Version: 4.10.39
Summary: UNKNOWN
Home-page: https://github.com/timfeirg/lain-cli
License: UNKNOWN
Platform: UNKNOWN
Requires-Python: >=3.8
Provides-Extra: all
Provides-Extra: tests
